pyspark_opendic/catalog.py
pyspark_opendic/client.py
pyspark_opendic/model/openapi_models.py
pyspark_opendic/model/__init__.py
pyspark_opendic/patterns/opendic_patterns.py
pyspark_opendic/prettyResponse.py
pyspark_opendic/__init__.py
pyspark_opendic-0.4.dist-info/WHEEL
pyspark_opendic-0.4.dist-info/entry_points.txt
pyspark_opendic-0.4.dist-info/METADATA
pyspark_opendic-0.4.dist-info/RECORD
