Metadata-Version: 2.3
Name: pyspark-opendic
Version: 0.4
Summary: Add your description here
Author: akongstad, carlbrr
Author-email: akongstad <kongstad@outlook.com>, carlbrr <carl99@live.dk>
Requires-Dist: pandas>=2.2.3
Requires-Dist: pydantic>=2.10.6
Requires-Dist: pyspark>=3.5.5
Requires-Dist: pytest-cov>=6.1.1
Requires-Dist: requests>=2.32.3
Requires-Python: >=3.9
